ambiguous/__init__.py
ambiguous/ambiguous.py
ambiguous/decorator.py
ambiguous/ops.py
ambiguous/thing_or_things.py
ambiguous-0.5.0.dist-info/LICENSE.txt
ambiguous-0.5.0.dist-info/METADATA
ambiguous-0.5.0.dist-info/WHEEL
ambiguous-0.5.0.dist-info/top_level.txt
ambiguous-0.5.0.dist-info/RECORD
