Metadata-Version: 2.1
Name: ambiguous
Version: 0.5.0
Summary: flexibility when you need it
Author: Daniel Pepper
License: The MIT License (MIT)
Project-URL: Homepage, https://github.com/dpep/py_ambiguous
Classifier: License :: OSI Approved :: MIT License
Classifier: Topic :: Utilities
Requires-Python: >=3
License-File: LICENSE.txt
